ovos_skill_boot_finished/LICENSE.md
ovos_skill_boot_finished/MANIFEST.in
ovos_skill_boot_finished/README.md
ovos_skill_boot_finished/__init__.py
ovos_skill_boot_finished/version.py
ovos_skill_boot_finished/locale/ca-es/skill.json
ovos_skill_boot_finished/locale/ca-es/dialog/confirm_no_speak_ready.dialog
ovos_skill_boot_finished/locale/ca-es/dialog/confirm_ready.dialog
ovos_skill_boot_finished/locale/ca-es/dialog/confirm_speak_ready.dialog
ovos_skill_boot_finished/locale/ca-es/dialog/deny_ready.dialog
ovos_skill_boot_finished/locale/ca-es/dialog/ready.dialog
ovos_skill_boot_finished/locale/ca-es/intent/are_you_ready.intent
ovos_skill_boot_finished/locale/ca-es/intent/disable_ready_notification.intent
ovos_skill_boot_finished/locale/ca-es/intent/enable_ready_notification.intent
ovos_skill_boot_finished/locale/da-dk/skill.json
ovos_skill_boot_finished/locale/da-dk/dialog/confirm_no_speak_ready.dialog
ovos_skill_boot_finished/locale/da-dk/dialog/confirm_ready.dialog
ovos_skill_boot_finished/locale/da-dk/dialog/confirm_speak_ready.dialog
ovos_skill_boot_finished/locale/da-dk/dialog/deny_ready.dialog
ovos_skill_boot_finished/locale/da-dk/dialog/ready.dialog
ovos_skill_boot_finished/locale/da-dk/intent/are_you_ready.intent
ovos_skill_boot_finished/locale/da-dk/intent/disable_ready_notification.intent
ovos_skill_boot_finished/locale/da-dk/intent/enable_ready_notification.intent
ovos_skill_boot_finished/locale/de-de/skill.json
ovos_skill_boot_finished/locale/de-de/dialog/confirm_no_speak_ready.dialog
ovos_skill_boot_finished/locale/de-de/dialog/confirm_ready.dialog
ovos_skill_boot_finished/locale/de-de/dialog/confirm_speak_ready.dialog
ovos_skill_boot_finished/locale/de-de/dialog/deny_ready.dialog
ovos_skill_boot_finished/locale/de-de/dialog/ready.dialog
ovos_skill_boot_finished/locale/de-de/intent/are_you_ready.intent
ovos_skill_boot_finished/locale/de-de/intent/disable_ready_notification.intent
ovos_skill_boot_finished/locale/de-de/intent/enable_ready_notification.intent
ovos_skill_boot_finished/ovos_skill_boot_finished.egg-info/PKG-INFO
ovos_skill_boot_finished/ovos_skill_boot_finished.egg-info/SOURCES.txt
ovos_skill_boot_finished/ovos_skill_boot_finished.egg-info/dependency_links.txt
ovos_skill_boot_finished/ovos_skill_boot_finished.egg-info/entry_points.txt
ovos_skill_boot_finished/ovos_skill_boot_finished.egg-info/top_level.txt
ovos_skill_boot_finished-0.5.0.dist-info/LICENSE.md
ovos_skill_boot_finished-0.5.0.dist-info/METADATA
ovos_skill_boot_finished-0.5.0.dist-info/WHEEL
ovos_skill_boot_finished-0.5.0.dist-info/entry_points.txt
ovos_skill_boot_finished-0.5.0.dist-info/top_level.txt
ovos_skill_boot_finished-0.5.0.dist-info/RECORD
