Metadata-Version: 2.1
Name: ovos-skill-boot-finished
Version: 0.5.0
Summary: OVOS finished booting skill
Home-page: https://github.com/OpenVoiceOS/ovos-skill-boot-finished
Author: OpenVoiceOS
Author-email: jarbasai@mailfence.com
License: Apache-2.0
Keywords: ovos skill plugin
License-File: LICENSE.md
